README.rst
setup.py
django_wxmgmt.egg-info/PKG-INFO
django_wxmgmt.egg-info/SOURCES.txt
django_wxmgmt.egg-info/dependency_links.txt
django_wxmgmt.egg-info/top_level.txt
wxmgmt/__init__.py
wxmgmt/admin.py
wxmgmt/apps.py
wxmgmt/models.py
wxmgmt/tests.py
wxmgmt/urls.py
wxmgmt/views.py
wxmgmt/migrations/0001_initial.py
wxmgmt/migrations/0002_remove_tenant_kefuxinxi.py
wxmgmt/migrations/0003_auto_20180210_0834.py
wxmgmt/migrations/__init__.py